./.gitignore
./PKG-INFO
./README.md
./pyproject.toml
./requirements-dev.lock
./requirements.lock
./uv.lock
./.github/workflows/lint.yml
./.github/workflows/publish.yml
./.github/workflows/tests.yml
./.vscode/settings.json
./metaboatrace/scrapers/__init__.py
./metaboatrace/scrapers/official/__init__.py
./metaboatrace/scrapers/official/website/__init__.py
./metaboatrace/scrapers/official/website/exceptions.py
./metaboatrace/scrapers/official/website/v1707/__init__.py
./metaboatrace/scrapers/official/website/v1707/decorators.py
./metaboatrace/scrapers/official/website/v1707/factories.py
./metaboatrace/scrapers/official/website/v1707/utils.py
./metaboatrace/scrapers/official/website/v1707/pages/__init__.py
./metaboatrace/scrapers/official/website/v1707/pages/event_holding_page/location.py
./metaboatrace/scrapers/official/website/v1707/pages/event_holding_page/scraping.py
./metaboatrace/scrapers/official/website/v1707/pages/monthly_schedule_page/__init__.py
./metaboatrace/scrapers/official/website/v1707/pages/monthly_schedule_page/location.py
./metaboatrace/scrapers/official/website/v1707/pages/monthly_schedule_page/scraping.py
./metaboatrace/scrapers/official/website/v1707/pages/pre_inspection_information_page/__init__.py
./metaboatrace/scrapers/official/website/v1707/pages/pre_inspection_information_page/location.py
./metaboatrace/scrapers/official/website/v1707/pages/pre_inspection_information_page/scraping.py
./metaboatrace/scrapers/official/website/v1707/pages/race/__init__.py
./metaboatrace/scrapers/official/website/v1707/pages/race/common.py
./metaboatrace/scrapers/official/website/v1707/pages/race/utils.py
./metaboatrace/scrapers/official/website/v1707/pages/race/before_information_page/__init__.py
./metaboatrace/scrapers/official/website/v1707/pages/race/before_information_page/location.py
./metaboatrace/scrapers/official/website/v1707/pages/race/before_information_page/scraping.py
./metaboatrace/scrapers/official/website/v1707/pages/race/entry_page/__init__.py
metaboatrace_scrapers-3.3.2.dist-info/METADATA
metaboatrace_scrapers-3.3.2.dist-info/WHEEL
metaboatrace_scrapers-3.3.2.dist-info/RECORD
