Metadata-Version: 2.4
Name: metaboatrace.scrapers
Version: 3.3.2
Summary: Scrapers for Japanese boatrace websites
Author-email: k0kishima <okishimaxyz@gmail.com>
License-Expression: MIT
Requires-Python: >=3.11
Requires-Dist: beautifulsoup4>=4.12.2
Requires-Dist: metaboatrace-models>=2.1.6
Requires-Dist: numpy>=1.25.2
Requires-Dist: pytest>=7.4.3
Requires-Dist: pytz>=2023.3.post1
Requires-Dist: types-pytz>=2023.3.1.1
Provides-Extra: dev
Requires-Dist: black>=23.7.0; extra == 'dev'
Requires-Dist: codecov>=2.1.13; extra == 'dev'
Requires-Dist: mypy>=1.4.1; extra == 'dev'
Requires-Dist: pytest-cov>=4.1.0; extra == 'dev'
Requires-Dist: pytest>=7.4.0; extra == 'dev'
